STA-663-final-project
biclustering
