Metadata-Version: 1.2
Name: STA-663-final-project
Version: 1.5
Summary: A python realization of Biclustering via Sparse Singular Value Decomposition
Home-page: https://github.com/xuetongli/STA-663-final-project
Author: Chunxiao Li, Xuetong Li
Author-email: xl222@duke.edu
License: UNKNOWN
Platform: UNKNOWN
Classifier: Development Status :: 3 - Alpha
Classifier: Intended Audience :: Developers
Classifier: Topic :: Software Development :: Libraries :: Python Modules
Classifier: License :: OSI Approved :: MIT License
Classifier: Programming Language :: Python :: 3
Classifier: Programming Language :: Python :: 3.4
Classifier: Programming Language :: Python :: 3.5
Classifier: Programming Language :: Python :: 3.6
Requires-Python: >=3
